socks5server/__init__.py
socks5server/__main__.py
socks5server/auth.py
socks5server/client_socks5.py
socks5server/enums.py
socks5server/exceptions.py
socks5server/packets/__init__.py
socks5server/packets/base.py
socks5server/packets/choose_auth_method.py
socks5server/packets/command_reply.py
socks5server/relay.py
socks5server/server.py
pysocks5server-0.1.2.dist-info/LICENSE
pysocks5server-0.1.2.dist-info/METADATA
pysocks5server-0.1.2.dist-info/WHEEL
pysocks5server-0.1.2.dist-info/RECORD
